bed/__init__.py
bed/design.py
bed/grid.py
bed/plot.py
bayesdesign-0.5.0.dist-info/LICENSE
bayesdesign-0.5.0.dist-info/METADATA
bayesdesign-0.5.0.dist-info/WHEEL
bayesdesign-0.5.0.dist-info/top_level.txt
bayesdesign-0.5.0.dist-info/RECORD
