Metadata-Version: 2.1
Name: bayesdesign
Version: 0.5.0
Summary: Package for Bayesian optimal experimental design
Home-page: https://github.com/dkirkby/bayesdesign
Author: David Kirkby
Author-email: dkirkby@uci.edu
Project-URL: Documentation, https://github.com/dkirkby/bayesdesign
Project-URL: Bug Reports, https://github.com/dkirkby/bayesdesign/issues
Project-URL: Source Code, https://github.com/dkirkby/bayesdesign
Keywords: bayes,optimization
Classifier: Development Status :: 4 - Beta
Classifier: Intended Audience :: Science/Research
Classifier: Topic :: Scientific/Engineering :: Astronomy
Classifier: Programming Language :: Python :: 3
Classifier: Programming Language :: Python :: 3 :: Only
Classifier: License :: OSI Approved :: MIT License
Classifier: Operating System :: OS Independent
Requires-Python: >=3.6
License-File: LICENSE
Requires-Dist: numpy
Provides-Extra: dev
Requires-Dist: check-manifest; extra == "dev"
